Seq.ciruits/MOD8count/asyn3bit/asyn3bit.v
module asyn3bit(
    input clk,clear,
    output reg [2:0]q 
);

always@( posedge clk or posedge clear)
      begin
        if(clear)
        begin
            q[0] <= 1'b0;
        end
        else begin
            q[0]<= ~q[0];
        end
      end
        
always@( negedge q[0] or posedge clear)
        begin 
            if (clear)
            begin
                q[1] <= 1'b0;
            end
            else begin
                q[1] <= ~q[1];
            end
        end
always@( negedge q[1] or posedge clear)
begin
    if(clear) begin
        q[2]<=1'b0;
    end
    else begin
    q[2]<= ~q[2];
    end
end
endmodule

Seq.ciruits/MOD8count/asyn3bit/asyn3bit_tb.v
module testbench;
reg clk ,clear;
wire [2:0]q;

asyn3bit dut(.clk(clk),.clear(clear),.q(q));

initial begin
    $dumpfile("asyn3bit.vcd");
    $dumpvars(0,testbench);
    $monitor($time," clk =%b,clear=%b,q=%b",clk,clear,q);

    clear =1;
   clk =0;

    #10 clear =0;
    #100 $finish;
end
always #5 clk =~clk;
endmodule

Seq.ciruits/MOD8count/asyn3bit/asyn3bit.vcd
$date
	Fri Aug 14 22:19:57 2026
$end
$version
	Icarus Verilog
$end
$timescale
	1s
$end
$scope module testbench $end
$var wire 3 ! q [2:0] $end
$var reg 1 " clear $end
$var reg 1 # clk $end
$scope module dut $end
$var wire 1 " clear $end
$var wire 1 # clk $end
$var reg 3 $ q [2:0] $end
$upscope $end
$upscope $end
$enddefinitions $end
$comment Show the parameter values. $end
$dumpall
$end
#0
$dumpvars
b0 $
0#
1"
b0 !
$end
#5
1#
#10
0#
0"
#15
b1 !
b1 $
1#
#20
0#
#25
b10 !
b10 $
1#
#30
0#
#35
b11 !
b11 $
1#
#40
0#
#45
b100 !
b100 $
1#
#50
0#
#55
b101 !
b101 $
1#
#60
0#
#65
b110 !
b110 $
1#
#70
0#
#75
b111 !
b111 $
1#
#80
0#
#85
b0 !
b0 $
1#
#90
0#
#95
b1 !
b1 $
1#
#100
0#
#105
b10 !
b10 $
1#
