Seq.ciruits/seqdetector/seqdetector.v
module seq_det(
    input in,clk,clear,
    output reg out
);
reg [1:0] state ,next_state;
parameter s0 = 2'b00 , 
 s1 = 2'b01 , s2 = 2'b10;

always@(posedge clk or posedge clear)
begin
    if(clear) begin
        state <= s0;
    end
    else begin 
        state <= next_state;
    end
end
;
always@(*)
begin
    case(state)
    s0:
    if(in) begin
        next_state = s1;
    end
    else begin
        next_state= s0;
    end
    s1:
    if(in) begin
        next_state = s1;
    end
    else begin
        next_state= s2;
    end
    s2:
    if(in) begin
        next_state=s1;
        out =1'b1;
    end
    else begin
        next_state= s0;
        out =1'b0;
    end
    default begin
        next_state =1'b0;
        out= 1'b0;
    end
    endcase
end
endmodule

Seq.ciruits/seqdetector/seqdetector_tb.v
module testbench;
    reg clk,clear,in;
    wire out;



seq_det dut(.clk(clk),.clear(clear),.in(in),.out(out));

initial begin
    $dumpfile("seqdet.vcd");
    $dumpvars(0,testbench);

    $monitor($time,"clk=%b,clear=%b,.in(in),.out(out)",
    clk,clear,in,out);
    clk=0;
    clear=1;
    in=0;
    #10 clear =0;
    #10 in=1;
    #10 in=0;
    #10 in=1;

    #100 $finish;
end
always #5 clk =~clk;
endmodule

Seq.ciruits/seqdetector/seqdet.vcd
$date
	Sat Aug 15 22:04:19 2026
$end
$version
	Icarus Verilog
$end
$timescale
	1s
$end
$scope module testbench $end
$var wire 1 ! out $end
$var reg 1 " clear $end
$var reg 1 # clk $end
$var reg 1 $ in $end
$scope module dut $end
$var wire 1 " clear $end
$var wire 1 # clk $end
$var wire 1 $ in $end
$var parameter 2 % s0 $end
$var parameter 2 & s1 $end
$var parameter 2 ' s2 $end
$var reg 2 ( next_state [1:0] $end
$var reg 1 ! out $end
$var reg 2 ) state [1:0] $end
$upscope $end
$upscope $end
$enddefinitions $end
$comment Show the parameter values. $end
$dumpall
b10 '
b1 &
b0 %
$end
#0
$dumpvars
b0 )
b0 (
0$
0#
1"
0!
$end
#5
1#
#10
0#
0"
#15
1#
#20
b1 (
0#
1$
#25
b1 )
1#
#30
b10 (
0#
0$
#35
b0 (
b10 )
1#
#40
1!
b1 (
0#
1$
#45
b1 )
1#
