mux16.v
module mux16_to_1(
    input [15:0] in,
    input [3:0] sel,
    output out
);

assign out = in[sel];

endmodule

mux16_tb.v
`timescale 1ns/1ps

module mux16_to_1_tb;

reg [15:0] in;
reg [3:0] sel;
wire out;

mux16_to_1 uut (
    .in(in),
    .sel(sel),
    .out(out)
);

initial begin
    $dumpfile("mux.vcd");
    $dumpvars(0, mux16_to_1_tb);

    in = 16'b1010101010101010;

    sel = 4'd0;  #10;
    sel = 4'd1;  #10;
    sel = 4'd2;  #10;
    sel = 4'd3;  #10;
    sel = 4'd4;  #10;
    sel = 4'd5;  #10;
    sel = 4'd6;  #10;
    sel = 4'd7;  #10;
    sel = 4'd8;  #10;
    sel = 4'd9;  #10;
    sel = 4'd10; #10;
    sel = 4'd11; #10;
    sel = 4'd12; #10;
    sel = 4'd13; #10;
    sel = 4'd14; #10;
    sel = 4'd15; #10;

    $finish;
end

initial begin
    $monitor("Time=%0t sel=%d out=%b", $time, sel, out);
end

endmodule

mux.vcd
$date
	Tue Jul 28 17:39:21 2026
$end
$version
	Icarus Verilog
$end
$timescale
	1ps
$end
$scope module mux16_to_1_tb $end
$var wire 1 ! out $end
$var reg 16 " in [15:0] $end
$var reg 4 # sel [3:0] $end
$scope module uut $end
$var wire 16 $ in [15:0] $end
$var wire 4 % sel [3:0] $end
$var wire 1 ! out $end
$upscope $end
$upscope $end
$enddefinitions $end
$comment Show the parameter values. $end
$dumpall
$end
#0
$dumpvars
b0 %
b1010101010101010 $
b0 #
b1010101010101010 "
0!
$end
#10000
1!
b1 #
b1 %
#20000
0!
b10 #
b10 %
#30000
1!
b11 #
b11 %
#40000
0!
b100 #
b100 %
#50000
1!
b101 #
b101 %
#60000
0!
b110 #
b110 %
#70000
1!
b111 #
b111 %
#80000
0!
b1000 #
b1000 %
#90000
1!
b1001 #
b1001 %
#100000
0!
b1010 #
b1010 %
#110000
1!
b1011 #
b1011 %
#120000
0!
b1100 #
b1100 %
#130000
1!
b1101 #
b1101 %
#140000
0!
b1110 #
b1110 %
#150000
1!
b1111 #
b1111 %
