Seq.ciruits/SIPO/sipo.v
module sipo(
    input in,clk,clear,
    output reg [3:0]q
);

always @(posedge clk)
      begin
        if(clear) begin
            q<= 4'b0000;
        end
        else begin
             q<= {q[2:0],in};
        end
      end
endmodule

Seq.ciruits/SIPO/sipo_tb.v
module testbench ;
reg in, clk,clear;
wire [3:0]q;

sipo dut(.in(in),.clk(clk),.clear(clear),.q(q));

initial 
    begin
        $dumpfile("sipo.vcd");
        $dumpvars(0,testbench);

        $monitor ($time," in=%b,clk=%b,clear=%b,q=%b",in,clk,clear,q);
        clk =0;
        clear =1;
        in =0;

        #10 clear =0;

        #10 in=1;
        #10 in=0 ;
        #10 in =1;
        #10 $finish;
    end
    always #5 clk =~clk;
endmodule

Seq.ciruits/SIPO/sipo.vcd
$date
	Wed Aug 12 00:09:28 2026
$end
$version
	Icarus Verilog
$end
$timescale
	1s
$end
$scope module testbench $end
$var wire 4 ! q [3:0] $end
$var reg 1 " clear $end
$var reg 1 # clk $end
$var reg 1 $ in $end
$scope module dut $end
$var wire 1 " clear $end
$var wire 1 # clk $end
$var wire 1 $ in $end
$var reg 4 % q [3:0] $end
$upscope $end
$upscope $end
$enddefinitions $end
$comment Show the parameter values. $end
$dumpall
$end
#0
$dumpvars
bx %
0$
0#
1"
bx !
$end
#5
b0 !
b0 %
1#
#10
0#
0"
#15
1#
#20
0#
1$
#25
b1 !
b1 %
1#
#30
0#
0$
#35
b10 !
b10 %
1#
#40
0#
1$
#45
b101 !
b101 %
1#
