Projects/4bitalu/4bitalu.v
module alu4bit(a,b,sel,carry,y,zero);
input [3:0]a,b;
input [2:0]sel;
output reg [3:0]y;
output reg carry,zero;

always@(*)
     begin
        case(sel)

          3'b000: begin
            y=a>>1;
            carry=0;
        end
        
        3'b001: begin
            y=a|b;
            carry=0;
        end
          3'b010: begin
            y=a&b;
        end
          3'b011: begin
            {carry,y}=a+b;
        end
          3'b100: begin
            {carry,y}=a-b;
        end
          3'b101: begin
            y=a^b;
            carry=0;
        end
          3'b110: begin
            y= ~b;
            carry=0;
        end
          3'b111: begin
            y=a<<1;
            carry=0;
        end
         default : begin
           y= 4'b0000;
           carry=0;
         end
        endcase 
     end
endmodule

Projects/4bitalu/4bitalu_tb.v
module testbench;
reg [3:0]a,b;
reg [2:0]sel;
wire [3:0]y;
wire carry,zero;

alu4bit dut(.a(a),.b(b),.sel(sel),.carry(carry),.y(y),.zero(zero));

initial
  begin
    $dumpfile("alu4bit.vcd");
    $dumpvars(0,testbench);

    $monitor($time,"a=%b,b=%b,sel=%b,carry=%b,y=%b,zero=%b",a,b,sel,carry,y,zero);
    #5 a=4'b0011; b=4'b1100;
    #5 sel=3'b000;
    #5 sel=3'b001;
    #5 sel=3'b010;
    #5 sel=3'b011;
    #5 sel=3'b100;
    #5 sel=3'b101;
    #5 sel=3'b110;
    #5 sel=3'b111;
    #10 $finish;
  end
endmodule

Projects/4bitalu/alu4bit.vcd
$date
	Thu Aug 06 22:15:38 2026
$end
$version
	Icarus Verilog
$end
$timescale
	1s
$end
$scope module testbench $end
$var wire 1 ! zero $end
$var wire 4 " y [3:0] $end
$var wire 1 # carry $end
$var reg 4 $ a [3:0] $end
$var reg 4 % b [3:0] $end
$var reg 3 & sel [2:0] $end
$scope module dut $end
$var wire 4 ' a [3:0] $end
$var wire 4 ( b [3:0] $end
$var wire 3 ) sel [2:0] $end
$var reg 1 # carry $end
$var reg 4 * y [3:0] $end
$var reg 1 ! zero $end
$upscope $end
$upscope $end
$enddefinitions $end
$comment Show the parameter values. $end
$dumpall
$end
#0
$dumpvars
bx *
bx )
bx (
bx '
bx &
bx %
bx $
x#
bx "
x!
$end
#5
0#
b0 "
b0 *
b1100 %
b1100 (
b11 $
b11 '
#10
b1 "
b1 *
b0 &
b0 )
#15
b1111 "
b1111 *
b1 &
b1 )
#20
b0 "
b0 *
b10 &
b10 )
#25
b1111 "
b1111 *
b11 &
b11 )
#30
1#
b111 "
b111 *
b100 &
b100 )
#35
0#
b1111 "
b1111 *
b101 &
b101 )
#40
b11 "
b11 *
b110 &
b110 )
#45
b110 "
b110 *
b111 &
b111 )
