Seq.ciruits/dff.v
module dff(d,clk,q);
input d,clk;
output reg q;
always@(posedge clk)
    begin
        q<=d;
    end
endmodule

Seq.ciruits/dff_tb.v
module testbench;
reg d,clk;
wire q;

dff dut(.d(d),.clk(clk),.q(q));

initial 
     begin 
        $dumpfile("dff.vcd");
        $dumpvars(0,testbench);

        $monitor($time," d=%b,q=%b,clk=%b",d,q,clk);
        
        clk =0;
        d=0;

        #10 d=1;
        #10 d=0;
        #10 d=1;
        #5 $finish ;
     end
     always #5 clk = ~clk;
endmodule

Seq.ciruits/dff.vcd
$date
	Mon Aug 10 22:19:27 2026
$end
$version
	Icarus Verilog
$end
$timescale
	1s
$end
$scope module testbench $end
$var wire 1 ! q $end
$var reg 1 " clk $end
$var reg 1 # d $end
$scope module dut $end
$var wire 1 " clk $end
$var wire 1 # d $end
$var reg 1 ! q $end
$upscope $end
$upscope $end
$enddefinitions $end
$comment Show the parameter values. $end
$dumpall
$end
#0
$dumpvars
0#
0"
x!
$end
#5
0!
1"
#10
0"
1#
#15
1!
1"
#20
0"
0#
#25
0!
1"
#30
0"
1#
#35
1!
1"
