Seq.ciruits/syn4bitcountup/upsyncount.v
module upsynco( 
    input clk , clear,
    output reg [3:0]q
);
always@( posedge clk or posedge clear) begin
    if(clear) begin
        q <= 4'b0000;
    end
    else begin
        q <= q + 1'b1;
    end
end
endmodule

Seq.ciruits/syn4bitcountup/upsyncount_tb.v
module testbench;
reg clk, clear;
wire [3:0]q;

upsynco dut(.clk(clk),.clear(clear),.q(q));

initial begin
    $dumpfile("upsynco.vcd");
    $dumpvars(0,testbench);

    $monitor($time,"clk=%b,clear=%b,q=%b",clk,clear,q);
    clk=0;
    clear=1;

    #10 clear=0;

    #100 $finish;
end
always #5 clk =~clk;
endmodule

Seq.ciruits/syn4bitcountup/upsynco.vcd
$date
	Fri Aug 14 22:25:30 2026
$end
$version
	Icarus Verilog
$end
$timescale
	1s
$end
$scope module testbench $end
$var wire 4 ! q [3:0] $end
$var reg 1 " clear $end
$var reg 1 # clk $end
$scope module dut $end
$var wire 1 " clear $end
$var wire 1 # clk $end
$var reg 4 $ q [3:0] $end
$upscope $end
$upscope $end
$enddefinitions $end
$comment Show the parameter values. $end
$dumpall
$end
#0
$dumpvars
b0 $
0#
1"
b0 !
$end
#5
1#
#10
0#
0"
#15
b1 !
b1 $
1#
#20
0#
#25
b10 !
b10 $
1#
#30
0#
#35
b11 !
b11 $
1#
#40
0#
#45
b100 !
b100 $
1#
#50
0#
#55
b101 !
b101 $
1#
#60
0#
#65
b110 !
b110 $
1#
#70
0#
#75
b111 !
b111 $
1#
#80
0#
#85
b1000 !
b1000 $
1#
#90
0#
#95
b1001 !
b1001 $
1#
#100
0#
#105
b1010 !
b1010 $
1#
