Seq.ciruits/4bitreg/4bitreg.v
module reg4bit(d,q,clk);
input [3:0]d;
input clk;
output reg [3:0]q;
always @(posedge clk)
     begin
        q<=d;
     end
endmodule

Seq.ciruits/4bitreg/4bitreg_tb.v
module testbench;
reg [3:0]d;
reg clk;
wire [3:0]q;

reg4bit dut(.d(d),.clk(clk),.q(q));

initial 
     begin 
        $dumpfile("reg4bit.vcd");
        $dumpvars(0,testbench);

        $monitor($time," d=%b,q=%b,clk=%b",d,q,clk);
        
        clk =0;
        d=4'b0000;

        #10 d=4'b0011;
        #10 d=4'b0101;
        #10 d=4'b1101;
        #10 d=4'b0110;
        #5 $finish ;
     end
     always #5 clk = ~clk;
endmodule

Seq.ciruits/4bitreg/reg4bit.vcd
$date
	Mon Aug 10 22:35:21 2026
$end
$version
	Icarus Verilog
$end
$timescale
	1s
$end
$scope module testbench $end
$var wire 4 ! q [3:0] $end
$var reg 1 " clk $end
$var reg 4 # d [3:0] $end
$scope module dut $end
$var wire 1 " clk $end
$var wire 4 $ d [3:0] $end
$var reg 4 % q [3:0] $end
$upscope $end
$upscope $end
$enddefinitions $end
$comment Show the parameter values. $end
$dumpall
$end
#0
$dumpvars
bx %
b0 $
b0 #
0"
bx !
$end
#5
b0 !
b0 %
1"
#10
0"
b11 #
b11 $
#15
b11 !
b11 %
1"
#20
0"
b101 #
b101 $
#25
b101 !
b101 %
1"
#30
0"
b1101 #
b1101 $
#35
b1101 !
b1101 %
1"
#40
0"
b110 #
b110 $
#45
b110 !
b110 %
1"
