Seq.ciruits/shiftreg/shiftreg.v
module shiftreg(clk,clear,d,in);
input clk,clear,in;
output reg d;
reg a,b,c;

always@(posedge clk )
     begin
        if(!clear) begin
        a<=0;
        b<=0;
        c<=0;
        d<=0;
        end
       
     
        else begin
        d<=c;
        c<=b;
        b<=a;
        a<=in;
        end
     end
endmodule

Seq.ciruits/shiftreg/shiftreg_tb.v
module testbench;
reg clk,clear,in;
wire d;
shiftreg dut(.d(d),.clk(clk),.clear(clear),.in(in));

initial
  begin
    clk =0;
    #5 clear =0;
    #5 in=0;
  end
  always #5 clk =~clk;
  initial begin
    #5 clear=1;
    #10 in=0;
    #10 in=1;
    #10 in=0;
    #10 in=1;
    #10 $finish;
 
  end
initial begin
    $dumpfile("shiftreg.vcd");
    $dumpvars(0,testbench);
    $monitor($time,"d=%b,clk=%b,clear=%b,in=%b",d,clk,clear,in);
end
endmodule

Seq.ciruits/shiftreg/shiftreg.vcd
$date
	Mon Aug 10 23:15:20 2026
$end
$version
	Icarus Verilog
$end
$timescale
	1s
$end
$scope module testbench $end
$var wire 1 ! d $end
$var reg 1 " clear $end
$var reg 1 # clk $end
$var reg 1 $ in $end
$scope module dut $end
$var wire 1 " clear $end
$var wire 1 # clk $end
$var wire 1 $ in $end
$var reg 1 % a $end
$var reg 1 & b $end
$var reg 1 ' c $end
$var reg 1 ! d $end
$upscope $end
$upscope $end
$enddefinitions $end
$comment Show the parameter values. $end
$dumpall
$end
#0
$dumpvars
x'
x&
x%
x$
0#
x"
x!
$end
#5
1#
1"
#10
0#
0$
#15
0%
1#
#20
0#
#25
1%
0&
1#
1$
#30
0#
#35
0%
1&
0'
1#
0$
#40
0#
#45
1%
0&
1'
0!
1#
1$
#50
0#
#55
1&
0'
1!
1#
