Seq.ciruits/updowncounter/updown.v
module updown(
    input clk,clear,up_down,
    output reg [3:0]q
);

always@(posedge clk or posedge clear) begin
    if(clear) begin
        q<= 4'b0000;
    end
    else if(up_down) begin
        q<= q + 1'b1;
    end
    else begin
        q<= q - 1'b1;
    end
end
endmodule

Seq.ciruits/updowncounter/updown_tb.v
module testbench;
reg clk, clear,up_down;
wire [3:0]q;

updown dut(.clk(clk),.clear(clear),.q(q),.up_down(up_down));

initial begin
    $dumpfile("updown.vcd");
    $dumpvars(0,testbench);

    $monitor($time,"clk=%b,clear=%b,q=%b,up_down=%b",clk,clear,q,up_down);
    clk=0;
    clear=1;
    up_down =1;

    #10 clear=0;
     #50 up_down =0;
    #100 $finish;
end
always #5 clk =~clk;
endmodule

Seq.ciruits/updowncounter/updown.vcd
$date
	Fri Aug 14 22:40:35 2026
$end
$version
	Icarus Verilog
$end
$timescale
	1s
$end
$scope module testbench $end
$var wire 4 ! q [3:0] $end
$var reg 1 " clear $end
$var reg 1 # clk $end
$var reg 1 $ up_down $end
$scope module dut $end
$var wire 1 " clear $end
$var wire 1 # clk $end
$var wire 1 $ up_down $end
$var reg 4 % q [3:0] $end
$upscope $end
$upscope $end
$enddefinitions $end
$comment Show the parameter values. $end
$dumpall
$end
#0
$dumpvars
b0 %
1$
0#
1"
b0 !
$end
#5
1#
#10
0#
0"
#15
b1 !
b1 %
1#
#20
0#
#25
b10 !
b10 %
1#
#30
0#
#35
b11 !
b11 %
1#
#40
0#
#45
b100 !
b100 %
1#
#50
0#
#55
b101 !
b101 %
1#
#60
0#
0$
#65
b100 !
b100 %
1#
#70
0#
#75
b11 !
b11 %
1#
#80
0#
#85
b10 !
b10 %
1#
#90
0#
#95
b1 !
b1 %
1#
#100
0#
#105
b0 !
b0 %
1#
#110
0#
#115
b1111 !
b1111 %
1#
#120
0#
#125
b1110 !
b1110 %
1#
#130
0#
#135
b1101 !
b1101 %
1#
#140
0#
#145
b1100 !
b1100 %
1#
#150
0#
#155
b1011 !
b1011 %
1#
