full_adder/full_adder.v
module fulladd(a,b,cin,s,cout);
input a,b,cin;  
output reg s,cout;
always @(a or b or cin)
begin
    s = a ^ b ^ cin;
    cout = (a & b) | (b & cin) | (a & cin);
end
endmodule

full_adder/full_adder_tb.v
module testbench;
reg a,b,cin;
wire s,cout;
fulladd uut(.a(a),.b(b),.cin(cin),.s(s),.cout(cout));
initial 
    begin
    $dumpfile("fulladd.vcd");
    $dumpvars(0, testbench);
    $monitor($time,"a=%b,b=%b,cin=%b,s=%b,cout=%b",a,b,cin,s,cout);
    #5 a=0;b=0;cin=0;
    #5 a=0;b=0;cin=1;
    #5 a=0;b=1;cin=0;
    #5 a=0;b=1;cin=1;
    #5 a=1;b=0;cin=0;
    #5 a=1;b=0;cin=1;
    #5 a=1;b=1;cin=0;
    #5 a=1;b=1;cin=1;
    #5 $finish ;
    end
endmodule

full_adder/fulladd.vcd
$date
	Fri Jul 31 23:30:02 2026
$end
$version
	Icarus Verilog
$end
$timescale
	1s
$end
$scope module testbench $end
$var wire 1 ! s $end
$var wire 1 " cout $end
$var reg 1 # a $end
$var reg 1 $ b $end
$var reg 1 % cin $end
$scope module uut $end
$var wire 1 # a $end
$var wire 1 $ b $end
$var wire 1 % cin $end
$var reg 1 " cout $end
$var reg 1 ! s $end
$upscope $end
$upscope $end
$enddefinitions $end
$comment Show the parameter values. $end
$dumpall
$end
#0
$dumpvars
x%
x$
x#
x"
x!
$end
#5
0"
0!
0%
0$
0#
#10
1!
1%
#15
0%
1$
#20
1"
0!
1%
#25
0"
1!
0%
0$
1#
#30
1"
0!
1%
#35
0%
1$
#40
1!
1%
